{
  "objectID": "6KM-17719-80847",
  "registration_code": "6KM-17719-80847",
  "sex": "Female",
  "zip_code": 293,
  "registered_date": "12/28/2020",
  "registrant_info": [
    {
      "REGISTRANT_CODE": "6KM-17719-80847",
      "ZIP_CODE": 293,
      "SEX": "Female",
      "REGISTERED_DATE": "12/28/2020",
      "TIME_ZONE": "US/Eastern",
      "RELATIONSHIP": "",
      "GUARDIAN_REGISTRANT_CODE": "",
      "REG_CODE_PREFIX": "6KM"
    }
  ],
  "vaccine_info": [
    {
      "REGISTRANT_CODE": "6KM-17719-80847",
      "MANUFACTURER": "Pfizer-BioNTech",
      "DOSE_NUMBER": 2,
      "VACCINATION_DATE": "01/18/2021",
      "COADMINISTERED": "",
      "COADMINISTERED_VAX": "",
      "REG_CODE_PREFIX": "6KM"
    },
    {
      "REGISTRANT_CODE": "6KM-17719-80847",
      "MANUFACTURER": "Pfizer-BioNTech",
      "DOSE_NUMBER": 3,
      "VACCINATION_DATE": "08/27/2021",
      "COADMINISTERED": "No",
      "COADMINISTERED_VAX": "",
      "REG_CODE_PREFIX": "6KM"
    },
    {
      "REGISTRANT_CODE": "6KM-17719-80847",
      "MANUFACTURER": "Pfizer-BioNTech",
      "DOSE_NUMBER": 1,
      "VACCINATION_DATE": "12/28/2020",
      "COADMINISTERED": "",
      "COADMINISTERED_VAX": "",
      "REG_CODE_PREFIX": "6KM"
    }
  ],
  "sro": [
    {
      "SURVEY_STATIC_ID": "vsafe-1-6-daily-dose2",
      "REGISTRANT_CODE": "6KM-17719-80847",
      "RESPONSE_ID": "s246592479731219148521614935939844074753",
      "STARTED_ON": "2021-01-22 00:00:00",
      "PT_NAME": "Respiratory tract congestion",
      "LLT_NAME": "Respiratory tract congestion",
      "MEDDRA_VERSION": 25.1,
      "ACTIVE": "YES",
      "NEWCODE": "NO",
      "DATEUPDATED": "",
      "DATECODED": "11/22/2022",
      "REG_CODE_PREFIX": "6KM"
    },
    {
      "SURVEY_STATIC_ID": "vsafe-1-6-daily-dose2",
      "REGISTRANT_CODE": "6KM-17719-80847",
      "RESPONSE_ID": "s246592479731219148521614935939844074753",
      "STARTED_ON": "2021-01-22 00:00:00",
      "PT_NAME": "Paranasal sinus discomfort",
      "LLT_NAME": "Sinus pressure",
      "MEDDRA_VERSION": 25.1,
      "ACTIVE": "YES",
      "NEWCODE": "NO",
      "DATEUPDATED": "",
      "DATECODED": "11/22/2022",
      "REG_CODE_PREFIX": "6KM"
    },
    {
      "SURVEY_STATIC_ID": "vsafe-7-day-dose3",
      "REGISTRANT_CODE": "6KM-17719-80847",
      "RESPONSE_ID": "s269982259615245359728879470461435119978",
      "STARTED_ON": "2021-09-03 00:00:00",
      "PT_NAME": "Diarrhoea",
      "LLT_NAME": "Loose stools",
      "MEDDRA_VERSION": 26.0,
      "ACTIVE": "YES",
      "NEWCODE": "NO",
      "DATEUPDATED": "",
      "DATECODED": "09/04/2023",
      "REG_CODE_PREFIX": "6KM"
    }
  ],
  "sd": [
    {
      "SURVEY_STATIC_ID": "vsafe-14-day-dose1",
      "REGISTRANT_CODE": "6KM-17719-80847",
      "RESPONSE_ID": "s245445475181857227555588622626266419059",
      "STARTED_ON": "2021-01-11 00:00:00",
      "PT_NAME": "Autoimmune disorder",
      "LLT_NAME": "Autoimmune disease flare up",
      "MEDDRA_VERSION": 25.1,
      "ACTIVE": "YES",
      "NEWCODE": "NO",
      "DATEUPDATED": "",
      "DATECODED": "11/10/2022",
      "REG_CODE_PREFIX": "6KM"
    },
    {
      "SURVEY_STATIC_ID": "vsafe-14-day-dose1",
      "REGISTRANT_CODE": "6KM-17719-80847",
      "RESPONSE_ID": "s245445475181857227555588622626266419059",
      "STARTED_ON": "2021-01-11 00:00:00",
      "PT_NAME": "Myalgia",
      "LLT_NAME": "Muscle pain",
      "MEDDRA_VERSION": 25.1,
      "ACTIVE": "YES",
      "NEWCODE": "NO",
      "DATEUPDATED": "",
      "DATECODED": "11/10/2022",
      "REG_CODE_PREFIX": "6KM"
    },
    {
      "SURVEY_STATIC_ID": "vsafe-14-day-dose1",
      "REGISTRANT_CODE": "6KM-17719-80847",
      "RESPONSE_ID": "s245445475181857227555588622626266419059",
      "STARTED_ON": "2021-01-11 00:00:00",
      "PT_NAME": "Malaise",
      "LLT_NAME": "Malaise",
      "MEDDRA_VERSION": 25.1,
      "ACTIVE": "YES",
      "NEWCODE": "NO",
      "DATEUPDATED": "",
      "DATECODED": "11/10/2022",
      "REG_CODE_PREFIX": "6KM"
    },
    {
      "SURVEY_STATIC_ID": "vsafe-14-day-dose1",
      "REGISTRANT_CODE": "6KM-17719-80847",
      "RESPONSE_ID": "s245445475181857227555588622626266419059",
      "STARTED_ON": "2021-01-11 00:00:00",
      "PT_NAME": "Fatigue",
      "LLT_NAME": "Fatigue",
      "MEDDRA_VERSION": 25.1,
      "ACTIVE": "YES",
      "NEWCODE": "NO",
      "DATEUPDATED": "",
      "DATECODED": "11/10/2022",
      "REG_CODE_PREFIX": "6KM"
    },
    {
      "SURVEY_STATIC_ID": "vsafe-14-day-dose1",
      "REGISTRANT_CODE": "6KM-17719-80847",
      "RESPONSE_ID": "s245445475181857227555588622626266419059",
      "STARTED_ON": "2021-01-11 00:00:00",
      "PT_NAME": "Headache",
      "LLT_NAME": "Headache",
      "MEDDRA_VERSION": 25.1,
      "ACTIVE": "YES",
      "NEWCODE": "NO",
      "DATEUPDATED": "",
      "DATECODED": "11/10/2022",
      "REG_CODE_PREFIX": "6KM"
    },
    {
      "SURVEY_STATIC_ID": "vsafe-14-day-dose1",
      "REGISTRANT_CODE": "6KM-17719-80847",
      "RESPONSE_ID": "s245445475181857227555588622626266419059",
      "STARTED_ON": "2021-01-11 00:00:00",
      "PT_NAME": "Pre-existing disease",
      "LLT_NAME": "Pre-existing disease",
      "MEDDRA_VERSION": 25.1,
      "ACTIVE": "YES",
      "NEWCODE": "YES",
      "DATEUPDATED": "01/20/2023",
      "DATECODED": "11/10/2022",
      "REG_CODE_PREFIX": "6KM"
    }
  ],
  "hcvo": [],
  "freetext": [
    {
      "REGISTRANT_CODE": "6KM-17719-80847",
      "SYMPTOMS_DESCRIPTION": "Flare of my autoimmune disease. Muscle pain, malaise, fatigue, headache.",
      "HEALTHCARE_VISITS_OTHER": "",
      "SYSTEMIC_REACTION_OTHER": "",
      "REG_CODE_PREFIX": "6KM"
    },
    {
      "REGISTRANT_CODE": "6KM-17719-80847",
      "SYMPTOMS_DESCRIPTION": "",
      "HEALTHCARE_VISITS_OTHER": "",
      "SYSTEMIC_REACTION_OTHER": "Congestion and sinus pressure.",
      "REG_CODE_PREFIX": "6KM"
    }
  ],
  "checkin_info": [
    {
      "SURVEY_STATIC_ID": "vsafe-1-6-daily-dose1",
      "REGISTRANT_CODE": "6KM-17719-80847",
      "RESPONSE_ID": "s244513594364426641803938826993695066431",
      "STARTED_ON": "01/02/2021",
      "STARTED_ON_TIME": "5:45:45 PM",
      "DAYS_SINCE": 5,
      "ABDOMINAL_PAIN": "",
      "CHILLS": "",
      "DIARRHEA": "",
      "FATIGUE": "",
      "FEELING_TODAY": "Good",
      "FEVER": "No",
      "HAD_SYMPTOMS": "",
      "HEADACHE": "",
      "HEALTH_IMPACT": "N/A",
      "HEALTH_NOW": "",
      "HEALTH_NOW_COMPARISON": "",
      "VACCINE_CAUSED_HEALTH_ISSUES": "",
      "HEALTHCARE_VISITS": "",
      "ITCHING": "",
      "JOINT_PAINS": "",
      "MUSCLE_OR_BODY_ACHES": "",
      "NAUSEA": "",
      "PAIN": "",
      "PREGNANT": "",
      "PREGNANCY_TEST": "",
      "RASH_OUTSIDE_INJECTION_SITE": "",
      "REDNESS": "",
      "SITE_REACTION": "None",
      "SWELLING": "",
      "SYSTEMIC_REACTION": "None",
      "TEMPERATURE_CELSIUS": "",
      "TEMPERATURE_FAHRENHEIT": "",
      "TEMPERATURE_READING": "",
      "TESTED_POSITIVE": "",
      "TESTED_POSITIVE_DATE": "",
      "VOMITING": "",
      "DURATION_MINS": "",
      "PREFERRED_LANGUAGE": "English",
      "REG_PREFIX": "6KM",
      "DOSE_NUM": "dose1",
      "TYPE": "daily",
      "MID_PHRASE": "-1-6-daily-",
      "SRO_MEDDRA": "",
      "SD_MEDDRA": "",
      "HCVO_MEDDRA": ""
    },
    {
      "SURVEY_STATIC_ID": "vsafe-1-6-daily-dose1",
      "REGISTRANT_CODE": "6KM-17719-80847",
      "RESPONSE_ID": "s244622798419446063501865915202354719159",
      "STARTED_ON": "01/03/2021",
      "STARTED_ON_TIME": "6:54:35 PM",
      "DAYS_SINCE": 6,
      "ABDOMINAL_PAIN": "",
      "CHILLS": "",
      "DIARRHEA": "",
      "FATIGUE": "",
      "FEELING_TODAY": "Good",
      "FEVER": "No",
      "HAD_SYMPTOMS": "",
      "HEADACHE": "",
      "HEALTH_IMPACT": "N/A",
      "HEALTH_NOW": "",
      "HEALTH_NOW_COMPARISON": "",
      "VACCINE_CAUSED_HEALTH_ISSUES": "",
      "HEALTHCARE_VISITS": "",
      "ITCHING": "",
      "JOINT_PAINS": "",
      "MUSCLE_OR_BODY_ACHES": "",
      "NAUSEA": "",
      "PAIN": "",
      "PREGNANT": "",
      "PREGNANCY_TEST": "",
      "RASH_OUTSIDE_INJECTION_SITE": "",
      "REDNESS": "",
      "SITE_REACTION": "None",
      "SWELLING": "",
      "SYSTEMIC_REACTION": "None",
      "TEMPERATURE_CELSIUS": "",
      "TEMPERATURE_FAHRENHEIT": "",
      "TEMPERATURE_READING": "",
      "TESTED_POSITIVE": "",
      "TESTED_POSITIVE_DATE": "",
      "VOMITING": "",
      "DURATION_MINS": "",
      "PREFERRED_LANGUAGE": "English",
      "REG_PREFIX": "6KM",
      "DOSE_NUM": "dose1",
      "TYPE": "daily",
      "MID_PHRASE": "-1-6-daily-",
      "SRO_MEDDRA": "",
      "SD_MEDDRA": "",
      "HCVO_MEDDRA": ""
    },
    {
      "SURVEY_STATIC_ID": "vsafe-7-day-dose1",
      "REGISTRANT_CODE": "6KM-17719-80847",
      "RESPONSE_ID": "s244711605893375549226631861726272467318",
      "STARTED_ON": "01/04/2021",
      "STARTED_ON_TIME": "3:15:44 PM",
      "DAYS_SINCE": 7,
      "ABDOMINAL_PAIN": "",
      "CHILLS": "",
      "DIARRHEA": "",
      "FATIGUE": "",
      "FEELING_TODAY": "Good",
      "FEVER": "No",
      "HAD_SYMPTOMS": "",
      "HEADACHE": "",
      "HEALTH_IMPACT": "N/A",
      "HEALTH_NOW": "",
      "HEALTH_NOW_COMPARISON": "",
      "VACCINE_CAUSED_HEALTH_ISSUES": "",
      "HEALTHCARE_VISITS": "",
      "ITCHING": "",
      "JOINT_PAINS": "",
      "MUSCLE_OR_BODY_ACHES": "",
      "NAUSEA": "",
      "PAIN": "",
      "PREGNANT": "",
      "PREGNANCY_TEST": "",
      "RASH_OUTSIDE_INJECTION_SITE": "",
      "REDNESS": "",
      "SITE_REACTION": "None",
      "SWELLING": "",
      "SYSTEMIC_REACTION": "None",
      "TEMPERATURE_CELSIUS": "",
      "TEMPERATURE_FAHRENHEIT": "",
      "TEMPERATURE_READING": "",
      "TESTED_POSITIVE": "",
      "TESTED_POSITIVE_DATE": "",
      "VOMITING": "",
      "DURATION_MINS": "",
      "PREFERRED_LANGUAGE": "English",
      "REG_PREFIX": "6KM",
      "DOSE_NUM": "dose1",
      "TYPE": "daily",
      "MID_PHRASE": "-7-day-",
      "SRO_MEDDRA": "",
      "SD_MEDDRA": "",
      "HCVO_MEDDRA": ""
    },
    {
      "SURVEY_STATIC_ID": "vsafe-14-day-dose1",
      "REGISTRANT_CODE": "6KM-17719-80847",
      "RESPONSE_ID": "s245445475181857227555588622626266419059",
      "STARTED_ON": "01/11/2021",
      "STARTED_ON_TIME": "3:52:32 PM",
      "DAYS_SINCE": 14,
      "ABDOMINAL_PAIN": "",
      "CHILLS": "",
      "DIARRHEA": "",
      "FATIGUE": "",
      "FEELING_TODAY": "Fair",
      "FEVER": "",
      "HAD_SYMPTOMS": "Yes",
      "HEADACHE": "",
      "HEALTH_IMPACT": "N/A",
      "HEALTH_NOW": "",
      "HEALTH_NOW_COMPARISON": "",
      "VACCINE_CAUSED_HEALTH_ISSUES": "",
      "HEALTHCARE_VISITS": "",
      "ITCHING": "",
      "JOINT_PAINS": "",
      "MUSCLE_OR_BODY_ACHES": "",
      "NAUSEA": "",
      "PAIN": "",
      "PREGNANT": "",
      "PREGNANCY_TEST": "",
      "RASH_OUTSIDE_INJECTION_SITE": "",
      "REDNESS": "",
      "SITE_REACTION": "",
      "SWELLING": "",
      "SYSTEMIC_REACTION": "",
      "TEMPERATURE_CELSIUS": "",
      "TEMPERATURE_FAHRENHEIT": "",
      "TEMPERATURE_READING": "",
      "TESTED_POSITIVE": "No",
      "TESTED_POSITIVE_DATE": "",
      "VOMITING": "",
      "DURATION_MINS": "",
      "PREFERRED_LANGUAGE": "English",
      "REG_PREFIX": "6KM",
      "DOSE_NUM": "dose1",
      "TYPE": "weekly",
      "MID_PHRASE": "-14-day-",
      "SRO_MEDDRA": "",
      "SD_MEDDRA": "Autoimmune disorder * Autoimmune disease flare up | Myalgia * Muscle pain | Malaise * Malaise | Fatigue * Fatigue | Headache * Headache | Pre-existing disease * Pre-existing disease",
      "HCVO_MEDDRA": ""
    },
    {
      "SURVEY_STATIC_ID": "vsafe-0-day-dose2",
      "REGISTRANT_CODE": "6KM-17719-80847",
      "RESPONSE_ID": "s246169857666857157634694935999792448808",
      "STARTED_ON": "01/18/2021",
      "STARTED_ON_TIME": "2:19:47 PM",
      "DAYS_SINCE": 0,
      "ABDOMINAL_PAIN": "",
      "CHILLS": "",
      "DIARRHEA": "",
      "FATIGUE": "",
      "FEELING_TODAY": "Good",
      "FEVER": "No",
      "HAD_SYMPTOMS": "",
      "HEADACHE": "",
      "HEALTH_IMPACT": "N/A",
      "HEALTH_NOW": "",
      "HEALTH_NOW_COMPARISON": "",
      "VACCINE_CAUSED_HEALTH_ISSUES": "",
      "HEALTHCARE_VISITS": "",
      "ITCHING": "",
      "JOINT_PAINS": "",
      "MUSCLE_OR_BODY_ACHES": "",
      "NAUSEA": "",
      "PAIN": "",
      "PREGNANT": "No",
      "PREGNANCY_TEST": "",
      "RASH_OUTSIDE_INJECTION_SITE": "",
      "REDNESS": "",
      "SITE_REACTION": "None",
      "SWELLING": "",
      "SYSTEMIC_REACTION": "None",
      "TEMPERATURE_CELSIUS": "",
      "TEMPERATURE_FAHRENHEIT": "",
      "TEMPERATURE_READING": "",
      "TESTED_POSITIVE": "",
      "TESTED_POSITIVE_DATE": "",
      "VOMITING": "",
      "DURATION_MINS": "",
      "PREFERRED_LANGUAGE": "English",
      "REG_PREFIX": "6KM",
      "DOSE_NUM": "dose2",
      "TYPE": "daily",
      "MID_PHRASE": "-0-day-",
      "SRO_MEDDRA": "",
      "SD_MEDDRA": "",
      "HCVO_MEDDRA": ""
    },
    {
      "SURVEY_STATIC_ID": "vsafe-1-6-daily-dose2",
      "REGISTRANT_CODE": "6KM-17719-80847",
      "RESPONSE_ID": "s246282036975460002647506281254334649906",
      "STARTED_ON": "01/19/2021",
      "STARTED_ON_TIME": "4:05:23 PM",
      "DAYS_SINCE": 1,
      "ABDOMINAL_PAIN": "",
      "CHILLS": "",
      "DIARRHEA": "",
      "FATIGUE": "Mild",
      "FEELING_TODAY": "Fair",
      "FEVER": "Yes",
      "HAD_SYMPTOMS": "",
      "HEADACHE": "Mild",
      "HEALTH_IMPACT": "N/A",
      "HEALTH_NOW": "",
      "HEALTH_NOW_COMPARISON": "",
      "VACCINE_CAUSED_HEALTH_ISSUES": "",
      "HEALTHCARE_VISITS": "",
      "ITCHING": "",
      "JOINT_PAINS": "Mild",
      "MUSCLE_OR_BODY_ACHES": "Mild",
      "NAUSEA": "",
      "PAIN": "Mild",
      "PREGNANT": "",
      "PREGNANCY_TEST": "",
      "RASH_OUTSIDE_INJECTION_SITE": "",
      "REDNESS": "",
      "SITE_REACTION": "Pain",
      "SWELLING": "",
      "SYSTEMIC_REACTION": "Headache:Joint pains:Muscle or body aches:Fatigue or tiredness",
      "TEMPERATURE_CELSIUS": "37.1",
      "TEMPERATURE_FAHRENHEIT": "98.8",
      "TEMPERATURE_READING": "Yes - in degrees Fahrenheit",
      "TESTED_POSITIVE": "",
      "TESTED_POSITIVE_DATE": "",
      "VOMITING": "",
      "DURATION_MINS": "",
      "PREFERRED_LANGUAGE": "English",
      "REG_PREFIX": "6KM",
      "DOSE_NUM": "dose2",
      "TYPE": "daily",
      "MID_PHRASE": "-1-6-daily-",
      "SRO_MEDDRA": "",
      "SD_MEDDRA": "",
      "HCVO_MEDDRA": ""
    },
    {
      "SURVEY_STATIC_ID": "vsafe-1-6-daily-dose2",
      "REGISTRANT_CODE": "6KM-17719-80847",
      "RESPONSE_ID": "s246415197445183817406212162873606181896",
      "STARTED_ON": "01/20/2021",
      "STARTED_ON_TIME": "10:41:12 PM",
      "DAYS_SINCE": 2,
      "ABDOMINAL_PAIN": "",
      "CHILLS": "",
      "DIARRHEA": "",
      "FATIGUE": "Mild",
      "FEELING_TODAY": "Fair",
      "FEVER": "Yes",
      "HAD_SYMPTOMS": "",
      "HEADACHE": "",
      "HEALTH_IMPACT": "N/A",
      "HEALTH_NOW": "",
      "HEALTH_NOW_COMPARISON": "",
      "VACCINE_CAUSED_HEALTH_ISSUES": "",
      "HEALTHCARE_VISITS": "",
      "ITCHING": "",
      "JOINT_PAINS": "",
      "MUSCLE_OR_BODY_ACHES": "Mild",
      "NAUSEA": "",
      "PAIN": "Mild",
      "PREGNANT": "",
      "PREGNANCY_TEST": "",
      "RASH_OUTSIDE_INJECTION_SITE": "",
      "REDNESS": "",
      "SITE_REACTION": "Pain",
      "SWELLING": "",
      "SYSTEMIC_REACTION": "Muscle or body aches:Fatigue or tiredness",
      "TEMPERATURE_CELSIUS": "",
      "TEMPERATURE_FAHRENHEIT": "",
      "TEMPERATURE_READING": "No - I didn't take my temperature",
      "TESTED_POSITIVE": "",
      "TESTED_POSITIVE_DATE": "",
      "VOMITING": "",
      "DURATION_MINS": "",
      "PREFERRED_LANGUAGE": "English",
      "REG_PREFIX": "6KM",
      "DOSE_NUM": "dose2",
      "TYPE": "daily",
      "MID_PHRASE": "-1-6-daily-",
      "SRO_MEDDRA": "",
      "SD_MEDDRA": "",
      "HCVO_MEDDRA": ""
    },
    {
      "SURVEY_STATIC_ID": "vsafe-1-6-daily-dose2",
      "REGISTRANT_CODE": "6KM-17719-80847",
      "RESPONSE_ID": "s246483009542068745659503860167125672715",
      "STARTED_ON": "01/21/2021",
      "STARTED_ON_TIME": "2:17:09 PM",
      "DAYS_SINCE": 3,
      "ABDOMINAL_PAIN": "",
      "CHILLS": "",
      "DIARRHEA": "",
      "FATIGUE": "",
      "FEELING_TODAY": "Good",
      "FEVER": "No",
      "HAD_SYMPTOMS": "",
      "HEADACHE": "",
      "HEALTH_IMPACT": "N/A",
      "HEALTH_NOW": "",
      "HEALTH_NOW_COMPARISON": "",
      "VACCINE_CAUSED_HEALTH_ISSUES": "",
      "HEALTHCARE_VISITS": "",
      "ITCHING": "",
      "JOINT_PAINS": "",
      "MUSCLE_OR_BODY_ACHES": "Mild",
      "NAUSEA": "",
      "PAIN": "",
      "PREGNANT": "",
      "PREGNANCY_TEST": "",
      "RASH_OUTSIDE_INJECTION_SITE": "",
      "REDNESS": "",
      "SITE_REACTION": "None",
      "SWELLING": "",
      "SYSTEMIC_REACTION": "Muscle or body aches",
      "TEMPERATURE_CELSIUS": "",
      "TEMPERATURE_FAHRENHEIT": "",
      "TEMPERATURE_READING": "",
      "TESTED_POSITIVE": "",
      "TESTED_POSITIVE_DATE": "",
      "VOMITING": "",
      "DURATION_MINS": "",
      "PREFERRED_LANGUAGE": "English",
      "REG_PREFIX": "6KM",
      "DOSE_NUM": "dose2",
      "TYPE": "daily",
      "MID_PHRASE": "-1-6-daily-",
      "SRO_MEDDRA": "",
      "SD_MEDDRA": "",
      "HCVO_MEDDRA": ""
    },
    {
      "SURVEY_STATIC_ID": "vsafe-1-6-daily-dose2",
      "REGISTRANT_CODE": "6KM-17719-80847",
      "RESPONSE_ID": "s246592479731219148521614935939844074753",
      "STARTED_ON": "01/22/2021",
      "STARTED_ON_TIME": "3:25:46 PM",
      "DAYS_SINCE": 4,
      "ABDOMINAL_PAIN": "",
      "CHILLS": "",
      "DIARRHEA": "",
      "FATIGUE": "Moderate",
      "FEELING_TODAY": "Poor",
      "FEVER": "Yes",
      "HAD_SYMPTOMS": "",
      "HEADACHE": "Moderate",
      "HEALTH_IMPACT": "Be unable to do your normal daily activities",
      "HEALTH_NOW": "",
      "HEALTH_NOW_COMPARISON": "",
      "VACCINE_CAUSED_HEALTH_ISSUES": "",
      "HEALTHCARE_VISITS": "",
      "ITCHING": "",
      "JOINT_PAINS": "",
      "MUSCLE_OR_BODY_ACHES": "Moderate",
      "NAUSEA": "",
      "PAIN": "",
      "PREGNANT": "",
      "PREGNANCY_TEST": "",
      "RASH_OUTSIDE_INJECTION_SITE": "",
      "REDNESS": "",
      "SITE_REACTION": "None",
      "SWELLING": "",
      "SYSTEMIC_REACTION": "Headache:Muscle or body aches:Fatigue or tiredness",
      "TEMPERATURE_CELSIUS": "",
      "TEMPERATURE_FAHRENHEIT": "",
      "TEMPERATURE_READING": "No - I didn't take my temperature",
      "TESTED_POSITIVE": "",
      "TESTED_POSITIVE_DATE": "",
      "VOMITING": "",
      "DURATION_MINS": "",
      "PREFERRED_LANGUAGE": "English",
      "REG_PREFIX": "6KM",
      "DOSE_NUM": "dose2",
      "TYPE": "daily",
      "MID_PHRASE": "-1-6-daily-",
      "SRO_MEDDRA": "Respiratory tract congestion * Respiratory tract congestion | Paranasal sinus discomfort * Sinus pressure",
      "SD_MEDDRA": "",
      "HCVO_MEDDRA": ""
    },
    {
      "SURVEY_STATIC_ID": "vsafe-1-6-daily-dose2",
      "REGISTRANT_CODE": "6KM-17719-80847",
      "RESPONSE_ID": "s246703890761015797878480817118664868494",
      "STARTED_ON": "01/23/2021",
      "STARTED_ON_TIME": "5:02:47 PM",
      "DAYS_SINCE": 5,
      "ABDOMINAL_PAIN": "",
      "CHILLS": "",
      "DIARRHEA": "",
      "FATIGUE": "",
      "FEELING_TODAY": "Good",
      "FEVER": "No",
      "HAD_SYMPTOMS": "",
      "HEADACHE": "",
      "HEALTH_IMPACT": "N/A",
      "HEALTH_NOW": "",
      "HEALTH_NOW_COMPARISON": "",
      "VACCINE_CAUSED_HEALTH_ISSUES": "",
      "HEALTHCARE_VISITS": "",
      "ITCHING": "",
      "JOINT_PAINS": "",
      "MUSCLE_OR_BODY_ACHES": "Mild",
      "NAUSEA": "",
      "PAIN": "",
      "PREGNANT": "",
      "PREGNANCY_TEST": "",
      "RASH_OUTSIDE_INJECTION_SITE": "",
      "REDNESS": "",
      "SITE_REACTION": "None",
      "SWELLING": "",
      "SYSTEMIC_REACTION": "Muscle or body aches",
      "TEMPERATURE_CELSIUS": "",
      "TEMPERATURE_FAHRENHEIT": "",
      "TEMPERATURE_READING": "",
      "TESTED_POSITIVE": "",
      "TESTED_POSITIVE_DATE": "",
      "VOMITING": "",
      "DURATION_MINS": "",
      "PREFERRED_LANGUAGE": "English",
      "REG_PREFIX": "6KM",
      "DOSE_NUM": "dose2",
      "TYPE": "daily",
      "MID_PHRASE": "-1-6-daily-",
      "SRO_MEDDRA": "",
      "SD_MEDDRA": "",
      "HCVO_MEDDRA": ""
    },
    {
      "SURVEY_STATIC_ID": "vsafe-1-6-daily-dose2",
      "REGISTRANT_CODE": "6KM-17719-80847",
      "RESPONSE_ID": "s246796265669311868173045053467864509654",
      "STARTED_ON": "01/24/2021",
      "STARTED_ON_TIME": "2:15:08 PM",
      "DAYS_SINCE": 6,
      "ABDOMINAL_PAIN": "",
      "CHILLS": "",
      "DIARRHEA": "",
      "FATIGUE": "",
      "FEELING_TODAY": "Good",
      "FEVER": "No",
      "HAD_SYMPTOMS": "",
      "HEADACHE": "",
      "HEALTH_IMPACT": "N/A",
      "HEALTH_NOW": "",
      "HEALTH_NOW_COMPARISON": "",
      "VACCINE_CAUSED_HEALTH_ISSUES": "",
      "HEALTHCARE_VISITS": "",
      "ITCHING": "",
      "JOINT_PAINS": "",
      "MUSCLE_OR_BODY_ACHES": "",
      "NAUSEA": "",
      "PAIN": "",
      "PREGNANT": "",
      "PREGNANCY_TEST": "",
      "RASH_OUTSIDE_INJECTION_SITE": "",
      "REDNESS": "",
      "SITE_REACTION": "None",
      "SWELLING": "",
      "SYSTEMIC_REACTION": "None",
      "TEMPERATURE_CELSIUS": "",
      "TEMPERATURE_FAHRENHEIT": "",
      "TEMPERATURE_READING": "",
      "TESTED_POSITIVE": "",
      "TESTED_POSITIVE_DATE": "",
      "VOMITING": "",
      "DURATION_MINS": "",
      "PREFERRED_LANGUAGE": "English",
      "REG_PREFIX": "6KM",
      "DOSE_NUM": "dose2",
      "TYPE": "daily",
      "MID_PHRASE": "-1-6-daily-",
      "SRO_MEDDRA": "",
      "SD_MEDDRA": "",
      "HCVO_MEDDRA": ""
    },
    {
      "SURVEY_STATIC_ID": "vsafe-7-day-dose2",
      "REGISTRANT_CODE": "6KM-17719-80847",
      "RESPONSE_ID": "s246903495547925018911572844920116492172",
      "STARTED_ON": "01/25/2021",
      "STARTED_ON_TIME": "2:53:50 PM",
      "DAYS_SINCE": 7,
      "ABDOMINAL_PAIN": "",
      "CHILLS": "",
      "DIARRHEA": "",
      "FATIGUE": "",
      "FEELING_TODAY": "Good",
      "FEVER": "No",
      "HAD_SYMPTOMS": "",
      "HEADACHE": "",
      "HEALTH_IMPACT": "N/A",
      "HEALTH_NOW": "",
      "HEALTH_NOW_COMPARISON": "",
      "VACCINE_CAUSED_HEALTH_ISSUES": "",
      "HEALTHCARE_VISITS": "",
      "ITCHING": "",
      "JOINT_PAINS": "",
      "MUSCLE_OR_BODY_ACHES": "",
      "NAUSEA": "",
      "PAIN": "",
      "PREGNANT": "",
      "PREGNANCY_TEST": "",
      "RASH_OUTSIDE_INJECTION_SITE": "",
      "REDNESS": "",
      "SITE_REACTION": "None",
      "SWELLING": "",
      "SYSTEMIC_REACTION": "None",
      "TEMPERATURE_CELSIUS": "",
      "TEMPERATURE_FAHRENHEIT": "",
      "TEMPERATURE_READING": "",
      "TESTED_POSITIVE": "",
      "TESTED_POSITIVE_DATE": "",
      "VOMITING": "",
      "DURATION_MINS": "",
      "PREFERRED_LANGUAGE": "English",
      "REG_PREFIX": "6KM",
      "DOSE_NUM": "dose2",
      "TYPE": "daily",
      "MID_PHRASE": "-7-day-",
      "SRO_MEDDRA": "",
      "SD_MEDDRA": "",
      "HCVO_MEDDRA": ""
    },
    {
      "SURVEY_STATIC_ID": "vsafe-14-day-dose2",
      "REGISTRANT_CODE": "6KM-17719-80847",
      "RESPONSE_ID": "s247632301924472573210932113430240974101",
      "STARTED_ON": "02/01/2021",
      "STARTED_ON_TIME": "2:23:05 PM",
      "DAYS_SINCE": 14,
      "ABDOMINAL_PAIN": "",
      "CHILLS": "",
      "DIARRHEA": "",
      "FATIGUE": "",
      "FEELING_TODAY": "Good",
      "FEVER": "",
      "HAD_SYMPTOMS": "No",
      "HEADACHE": "",
      "HEALTH_IMPACT": "",
      "HEALTH_NOW": "",
      "HEALTH_NOW_COMPARISON": "",
      "VACCINE_CAUSED_HEALTH_ISSUES": "",
      "HEALTHCARE_VISITS": "",
      "ITCHING": "",
      "JOINT_PAINS": "",
      "MUSCLE_OR_BODY_ACHES": "",
      "NAUSEA": "",
      "PAIN": "",
      "PREGNANT": "",
      "PREGNANCY_TEST": "",
      "RASH_OUTSIDE_INJECTION_SITE": "",
      "REDNESS": "",
      "SITE_REACTION": "",
      "SWELLING": "",
      "SYSTEMIC_REACTION": "",
      "TEMPERATURE_CELSIUS": "",
      "TEMPERATURE_FAHRENHEIT": "",
      "TEMPERATURE_READING": "",
      "TESTED_POSITIVE": "No",
      "TESTED_POSITIVE_DATE": "",
      "VOMITING": "",
      "DURATION_MINS": "",
      "PREFERRED_LANGUAGE": "English",
      "REG_PREFIX": "6KM",
      "DOSE_NUM": "dose2",
      "TYPE": "weekly",
      "MID_PHRASE": "-14-day-",
      "SRO_MEDDRA": "",
      "SD_MEDDRA": "",
      "HCVO_MEDDRA": ""
    },
    {
      "SURVEY_STATIC_ID": "vsafe-21-day-dose2",
      "REGISTRANT_CODE": "6KM-17719-80847",
      "RESPONSE_ID": "s248366792779310598543017698980325377218",
      "STARTED_ON": "02/08/2021",
      "STARTED_ON_TIME": "3:15:51 PM",
      "DAYS_SINCE": 21,
      "ABDOMINAL_PAIN": "",
      "CHILLS": "",
      "DIARRHEA": "",
      "FATIGUE": "",
      "FEELING_TODAY": "Good",
      "FEVER": "",
      "HAD_SYMPTOMS": "No",
      "HEADACHE": "",
      "HEALTH_IMPACT": "",
      "HEALTH_NOW": "",
      "HEALTH_NOW_COMPARISON": "",
      "VACCINE_CAUSED_HEALTH_ISSUES": "",
      "HEALTHCARE_VISITS": "",
      "ITCHING": "",
      "JOINT_PAINS": "",
      "MUSCLE_OR_BODY_ACHES": "",
      "NAUSEA": "",
      "PAIN": "",
      "PREGNANT": "",
      "PREGNANCY_TEST": "No",
      "RASH_OUTSIDE_INJECTION_SITE": "",
      "REDNESS": "",
      "SITE_REACTION": "",
      "SWELLING": "",
      "SYSTEMIC_REACTION": "",
      "TEMPERATURE_CELSIUS": "",
      "TEMPERATURE_FAHRENHEIT": "",
      "TEMPERATURE_READING": "",
      "TESTED_POSITIVE": "No",
      "TESTED_POSITIVE_DATE": "",
      "VOMITING": "",
      "DURATION_MINS": "",
      "PREFERRED_LANGUAGE": "English",
      "REG_PREFIX": "6KM",
      "DOSE_NUM": "dose2",
      "TYPE": "weekly",
      "MID_PHRASE": "-21-day-",
      "SRO_MEDDRA": "",
      "SD_MEDDRA": "",
      "HCVO_MEDDRA": ""
    },
    {
      "SURVEY_STATIC_ID": "vsafe-28-day-dose2",
      "REGISTRANT_CODE": "6KM-17719-80847",
      "RESPONSE_ID": "s249093936124821401339671284722050989898",
      "STARTED_ON": "02/15/2021",
      "STARTED_ON_TIME": "2:11:53 PM",
      "DAYS_SINCE": 28,
      "ABDOMINAL_PAIN": "",
      "CHILLS": "",
      "DIARRHEA": "",
      "FATIGUE": "",
      "FEELING_TODAY": "Fair",
      "FEVER": "",
      "HAD_SYMPTOMS": "No",
      "HEADACHE": "",
      "HEALTH_IMPACT": "",
      "HEALTH_NOW": "",
      "HEALTH_NOW_COMPARISON": "",
      "VACCINE_CAUSED_HEALTH_ISSUES": "",
      "HEALTHCARE_VISITS": "",
      "ITCHING": "",
      "JOINT_PAINS": "",
      "MUSCLE_OR_BODY_ACHES": "",
      "NAUSEA": "",
      "PAIN": "",
      "PREGNANT": "",
      "PREGNANCY_TEST": "",
      "RASH_OUTSIDE_INJECTION_SITE": "",
      "REDNESS": "",
      "SITE_REACTION": "",
      "SWELLING": "",
      "SYSTEMIC_REACTION": "",
      "TEMPERATURE_CELSIUS": "",
      "TEMPERATURE_FAHRENHEIT": "",
      "TEMPERATURE_READING": "",
      "TESTED_POSITIVE": "No",
      "TESTED_POSITIVE_DATE": "",
      "VOMITING": "",
      "DURATION_MINS": "",
      "PREFERRED_LANGUAGE": "English",
      "REG_PREFIX": "6KM",
      "DOSE_NUM": "dose2",
      "TYPE": "weekly",
      "MID_PHRASE": "-28-day-",
      "SRO_MEDDRA": "",
      "SD_MEDDRA": "",
      "HCVO_MEDDRA": ""
    },
    {
      "SURVEY_STATIC_ID": "vsafe-35-day-dose2",
      "REGISTRANT_CODE": "6KM-17719-80847",
      "RESPONSE_ID": "s249829136997054697766460391900440092731",
      "STARTED_ON": "02/22/2021",
      "STARTED_ON_TIME": "3:09:09 PM",
      "DAYS_SINCE": 35,
      "ABDOMINAL_PAIN": "",
      "CHILLS": "",
      "DIARRHEA": "",
      "FATIGUE": "",
      "FEELING_TODAY": "Good",
      "FEVER": "",
      "HAD_SYMPTOMS": "No",
      "HEADACHE": "",
      "HEALTH_IMPACT": "",
      "HEALTH_NOW": "",
      "HEALTH_NOW_COMPARISON": "",
      "VACCINE_CAUSED_HEALTH_ISSUES": "",
      "HEALTHCARE_VISITS": "",
      "ITCHING": "",
      "JOINT_PAINS": "",
      "MUSCLE_OR_BODY_ACHES": "",
      "NAUSEA": "",
      "PAIN": "",
      "PREGNANT": "",
      "PREGNANCY_TEST": "",
      "RASH_OUTSIDE_INJECTION_SITE": "",
      "REDNESS": "",
      "SITE_REACTION": "",
      "SWELLING": "",
      "SYSTEMIC_REACTION": "",
      "TEMPERATURE_CELSIUS": "",
      "TEMPERATURE_FAHRENHEIT": "",
      "TEMPERATURE_READING": "",
      "TESTED_POSITIVE": "No",
      "TESTED_POSITIVE_DATE": "",
      "VOMITING": "",
      "DURATION_MINS": "0.35",
      "PREFERRED_LANGUAGE": "English",
      "REG_PREFIX": "6KM",
      "DOSE_NUM": "dose2",
      "TYPE": "weekly",
      "MID_PHRASE": "-35-day-",
      "SRO_MEDDRA": "",
      "SD_MEDDRA": "",
      "HCVO_MEDDRA": ""
    },
    {
      "SURVEY_STATIC_ID": "vsafe-6-month-dose3",
      "REGISTRANT_CODE": "6KM-17719-80847",
      "RESPONSE_ID": "s288262791445851766962885833635876438265",
      "STARTED_ON": "02/25/2022",
      "STARTED_ON_TIME": "2:06:46 PM",
      "DAYS_SINCE": 182,
      "ABDOMINAL_PAIN": "",
      "CHILLS": "",
      "DIARRHEA": "",
      "FATIGUE": "",
      "FEELING_TODAY": "Good",
      "FEVER": "",
      "HAD_SYMPTOMS": "Yes",
      "HEADACHE": "",
      "HEALTH_IMPACT": "Be unable to work or attend school:Be unable to do your normal daily activities:Get care from a doctor or other healthcare professional",
      "HEALTH_NOW": "",
      "HEALTH_NOW_COMPARISON": "About the same",
      "VACCINE_CAUSED_HEALTH_ISSUES": "",
      "HEALTHCARE_VISITS": "Telehealth, virtual health, or email health consultation",
      "ITCHING": "",
      "JOINT_PAINS": "",
      "MUSCLE_OR_BODY_ACHES": "",
      "NAUSEA": "",
      "PAIN": "",
      "PREGNANT": "",
      "PREGNANCY_TEST": "No",
      "RASH_OUTSIDE_INJECTION_SITE": "",
      "REDNESS": "",
      "SITE_REACTION": "",
      "SWELLING": "",
      "SYSTEMIC_REACTION": "",
      "TEMPERATURE_CELSIUS": "",
      "TEMPERATURE_FAHRENHEIT": "",
      "TEMPERATURE_READING": "",
      "TESTED_POSITIVE": "Yes",
      "TESTED_POSITIVE_DATE": "01/29/2022",
      "VOMITING": "",
      "DURATION_MINS": "0.92",
      "PREFERRED_LANGUAGE": "English",
      "REG_PREFIX": "6KM",
      "DOSE_NUM": "dose3",
      "TYPE": "monthly",
      "MID_PHRASE": "-6-month-",
      "SRO_MEDDRA": "",
      "SD_MEDDRA": "",
      "HCVO_MEDDRA": ""
    },
    {
      "SURVEY_STATIC_ID": "vsafe-42-day-dose2",
      "REGISTRANT_CODE": "6KM-17719-80847",
      "RESPONSE_ID": "s250555818422298802521798523251159884126",
      "STARTED_ON": "03/01/2021",
      "STARTED_ON_TIME": "2:05:29 PM",
      "DAYS_SINCE": 42,
      "ABDOMINAL_PAIN": "",
      "CHILLS": "",
      "DIARRHEA": "",
      "FATIGUE": "",
      "FEELING_TODAY": "Good",
      "FEVER": "",
      "HAD_SYMPTOMS": "No",
      "HEADACHE": "",
      "HEALTH_IMPACT": "",
      "HEALTH_NOW": "Fair",
      "HEALTH_NOW_COMPARISON": "About the same",
      "VACCINE_CAUSED_HEALTH_ISSUES": "",
      "HEALTHCARE_VISITS": "",
      "ITCHING": "",
      "JOINT_PAINS": "",
      "MUSCLE_OR_BODY_ACHES": "",
      "NAUSEA": "",
      "PAIN": "",
      "PREGNANT": "",
      "PREGNANCY_TEST": "No",
      "RASH_OUTSIDE_INJECTION_SITE": "",
      "REDNESS": "",
      "SITE_REACTION": "",
      "SWELLING": "",
      "SYSTEMIC_REACTION": "",
      "TEMPERATURE_CELSIUS": "",
      "TEMPERATURE_FAHRENHEIT": "",
      "TEMPERATURE_READING": "",
      "TESTED_POSITIVE": "No",
      "TESTED_POSITIVE_DATE": "",
      "VOMITING": "",
      "DURATION_MINS": "0.53",
      "PREFERRED_LANGUAGE": "English",
      "REG_PREFIX": "6KM",
      "DOSE_NUM": "dose2",
      "TYPE": "weekly",
      "MID_PHRASE": "-42-day-",
      "SRO_MEDDRA": "",
      "SD_MEDDRA": "",
      "HCVO_MEDDRA": ""
    },
    {
      "SURVEY_STATIC_ID": "vsafe-3-month-dose2",
      "REGISTRANT_CODE": "6KM-17719-80847",
      "RESPONSE_ID": "s255671782965416079167589683807476421677",
      "STARTED_ON": "04/19/2021",
      "STARTED_ON_TIME": "2:35:54 PM",
      "DAYS_SINCE": 91,
      "ABDOMINAL_PAIN": "",
      "CHILLS": "",
      "DIARRHEA": "",
      "FATIGUE": "",
      "FEELING_TODAY": "Good",
      "FEVER": "",
      "HAD_SYMPTOMS": "No",
      "HEADACHE": "",
      "HEALTH_IMPACT": "",
      "HEALTH_NOW": "",
      "HEALTH_NOW_COMPARISON": "About the same",
      "VACCINE_CAUSED_HEALTH_ISSUES": "",
      "HEALTHCARE_VISITS": "",
      "ITCHING": "",
      "JOINT_PAINS": "",
      "MUSCLE_OR_BODY_ACHES": "",
      "NAUSEA": "",
      "PAIN": "",
      "PREGNANT": "",
      "PREGNANCY_TEST": "No",
      "RASH_OUTSIDE_INJECTION_SITE": "",
      "REDNESS": "",
      "SITE_REACTION": "",
      "SWELLING": "",
      "SYSTEMIC_REACTION": "",
      "TEMPERATURE_CELSIUS": "",
      "TEMPERATURE_FAHRENHEIT": "",
      "TEMPERATURE_READING": "",
      "TESTED_POSITIVE": "No",
      "TESTED_POSITIVE_DATE": "",
      "VOMITING": "",
      "DURATION_MINS": "0.38",
      "PREFERRED_LANGUAGE": "English",
      "REG_PREFIX": "6KM",
      "DOSE_NUM": "dose2",
      "TYPE": "monthly",
      "MID_PHRASE": "-3-month-",
      "SRO_MEDDRA": "",
      "SD_MEDDRA": "",
      "HCVO_MEDDRA": ""
    },
    {
      "SURVEY_STATIC_ID": "vsafe-6-month-dose2",
      "REGISTRANT_CODE": "6KM-17719-80847",
      "RESPONSE_ID": "s265176387140615062728983199191786988277",
      "STARTED_ON": "07/19/2021",
      "STARTED_ON_TIME": "2:31:47 PM",
      "DAYS_SINCE": 182,
      "ABDOMINAL_PAIN": "",
      "CHILLS": "",
      "DIARRHEA": "",
      "FATIGUE": "",
      "FEELING_TODAY": "Fair",
      "FEVER": "",
      "HAD_SYMPTOMS": "No",
      "HEADACHE": "",
      "HEALTH_IMPACT": "",
      "HEALTH_NOW": "",
      "HEALTH_NOW_COMPARISON": "About the same",
      "VACCINE_CAUSED_HEALTH_ISSUES": "",
      "HEALTHCARE_VISITS": "",
      "ITCHING": "",
      "JOINT_PAINS": "",
      "MUSCLE_OR_BODY_ACHES": "",
      "NAUSEA": "",
      "PAIN": "",
      "PREGNANT": "",
      "PREGNANCY_TEST": "No",
      "RASH_OUTSIDE_INJECTION_SITE": "",
      "REDNESS": "",
      "SITE_REACTION": "",
      "SWELLING": "",
      "SYSTEMIC_REACTION": "",
      "TEMPERATURE_CELSIUS": "",
      "TEMPERATURE_FAHRENHEIT": "",
      "TEMPERATURE_READING": "",
      "TESTED_POSITIVE": "No",
      "TESTED_POSITIVE_DATE": "",
      "VOMITING": "",
      "DURATION_MINS": "0.47",
      "PREFERRED_LANGUAGE": "English",
      "REG_PREFIX": "6KM",
      "DOSE_NUM": "dose2",
      "TYPE": "monthly",
      "MID_PHRASE": "-6-month-",
      "SRO_MEDDRA": "",
      "SD_MEDDRA": "",
      "HCVO_MEDDRA": ""
    },
    {
      "SURVEY_STATIC_ID": "vsafe-1-6-daily-dose3",
      "REGISTRANT_CODE": "6KM-17719-80847",
      "RESPONSE_ID": "s269383242952476611102740925273604798507",
      "STARTED_ON": "08/28/2021",
      "STARTED_ON_TIME": "9:16:31 PM",
      "DAYS_SINCE": 1,
      "ABDOMINAL_PAIN": "",
      "CHILLS": "",
      "DIARRHEA": "",
      "FATIGUE": "Moderate",
      "FEELING_TODAY": "Fair",
      "FEVER": "Yes",
      "HAD_SYMPTOMS": "",
      "HEADACHE": "",
      "HEALTH_IMPACT": "N/A",
      "HEALTH_NOW": "",
      "HEALTH_NOW_COMPARISON": "",
      "VACCINE_CAUSED_HEALTH_ISSUES": "",
      "HEALTHCARE_VISITS": "",
      "ITCHING": "",
      "JOINT_PAINS": "Mild",
      "MUSCLE_OR_BODY_ACHES": "Mild",
      "NAUSEA": "",
      "PAIN": "Mild",
      "PREGNANT": "No",
      "PREGNANCY_TEST": "",
      "RASH_OUTSIDE_INJECTION_SITE": "",
      "REDNESS": "",
      "SITE_REACTION": "Pain",
      "SWELLING": "",
      "SYSTEMIC_REACTION": "Joint pains:Muscle or body aches:Fatigue or tiredness",
      "TEMPERATURE_CELSIUS": "",
      "TEMPERATURE_FAHRENHEIT": "",
      "TEMPERATURE_READING": "No - I didn't take my temperature",
      "TESTED_POSITIVE": "",
      "TESTED_POSITIVE_DATE": "",
      "VOMITING": "",
      "DURATION_MINS": "0.87",
      "PREFERRED_LANGUAGE": "English",
      "REG_PREFIX": "6KM",
      "DOSE_NUM": "dose3",
      "TYPE": "daily",
      "MID_PHRASE": "-1-6-daily-",
      "SRO_MEDDRA": "",
      "SD_MEDDRA": "",
      "HCVO_MEDDRA": ""
    },
    {
      "SURVEY_STATIC_ID": "vsafe-1-6-daily-dose3",
      "REGISTRANT_CODE": "6KM-17719-80847",
      "RESPONSE_ID": "s269466450571720109585525810924173826439",
      "STARTED_ON": "08/29/2021",
      "STARTED_ON_TIME": "4:19:27 PM",
      "DAYS_SINCE": 2,
      "ABDOMINAL_PAIN": "",
      "CHILLS": "",
      "DIARRHEA": "",
      "FATIGUE": "",
      "FEELING_TODAY": "Good",
      "FEVER": "No",
      "HAD_SYMPTOMS": "",
      "HEADACHE": "",
      "HEALTH_IMPACT": "N/A",
      "HEALTH_NOW": "",
      "HEALTH_NOW_COMPARISON": "",
      "VACCINE_CAUSED_HEALTH_ISSUES": "",
      "HEALTHCARE_VISITS": "",
      "ITCHING": "",
      "JOINT_PAINS": "",
      "MUSCLE_OR_BODY_ACHES": "",
      "NAUSEA": "",
      "PAIN": "",
      "PREGNANT": "",
      "PREGNANCY_TEST": "",
      "RASH_OUTSIDE_INJECTION_SITE": "",
      "REDNESS": "",
      "SITE_REACTION": "None",
      "SWELLING": "",
      "SYSTEMIC_REACTION": "None",
      "TEMPERATURE_CELSIUS": "",
      "TEMPERATURE_FAHRENHEIT": "",
      "TEMPERATURE_READING": "",
      "TESTED_POSITIVE": "",
      "TESTED_POSITIVE_DATE": "",
      "VOMITING": "",
      "DURATION_MINS": "0.3",
      "PREFERRED_LANGUAGE": "English",
      "REG_PREFIX": "6KM",
      "DOSE_NUM": "dose3",
      "TYPE": "daily",
      "MID_PHRASE": "-1-6-daily-",
      "SRO_MEDDRA": "",
      "SD_MEDDRA": "",
      "HCVO_MEDDRA": ""
    },
    {
      "SURVEY_STATIC_ID": "vsafe-1-6-daily-dose3",
      "REGISTRANT_CODE": "6KM-17719-80847",
      "RESPONSE_ID": "s269561644285939047130374289161137587967",
      "STARTED_ON": "08/30/2021",
      "STARTED_ON_TIME": "2:06:09 PM",
      "DAYS_SINCE": 3,
      "ABDOMINAL_PAIN": "",
      "CHILLS": "",
      "DIARRHEA": "",
      "FATIGUE": "Mild",
      "FEELING_TODAY": "Good",
      "FEVER": "No",
      "HAD_SYMPTOMS": "",
      "HEADACHE": "",
      "HEALTH_IMPACT": "N/A",
      "HEALTH_NOW": "",
      "HEALTH_NOW_COMPARISON": "",
      "VACCINE_CAUSED_HEALTH_ISSUES": "",
      "HEALTHCARE_VISITS": "",
      "ITCHING": "",
      "JOINT_PAINS": "",
      "MUSCLE_OR_BODY_ACHES": "",
      "NAUSEA": "",
      "PAIN": "",
      "PREGNANT": "",
      "PREGNANCY_TEST": "",
      "RASH_OUTSIDE_INJECTION_SITE": "",
      "REDNESS": "",
      "SITE_REACTION": "None",
      "SWELLING": "",
      "SYSTEMIC_REACTION": "Fatigue or tiredness",
      "TEMPERATURE_CELSIUS": "",
      "TEMPERATURE_FAHRENHEIT": "",
      "TEMPERATURE_READING": "",
      "TESTED_POSITIVE": "",
      "TESTED_POSITIVE_DATE": "",
      "VOMITING": "",
      "DURATION_MINS": "0.28",
      "PREFERRED_LANGUAGE": "English",
      "REG_PREFIX": "6KM",
      "DOSE_NUM": "dose3",
      "TYPE": "daily",
      "MID_PHRASE": "-1-6-daily-",
      "SRO_MEDDRA": "",
      "SD_MEDDRA": "",
      "HCVO_MEDDRA": ""
    },
    {
      "SURVEY_STATIC_ID": "vsafe-1-6-daily-dose3",
      "REGISTRANT_CODE": "6KM-17719-80847",
      "RESPONSE_ID": "s269666307648804809820665729034736009732",
      "STARTED_ON": "08/31/2021",
      "STARTED_ON_TIME": "2:09:14 PM",
      "DAYS_SINCE": 4,
      "ABDOMINAL_PAIN": "",
      "CHILLS": "",
      "DIARRHEA": "",
      "FATIGUE": "",
      "FEELING_TODAY": "Good",
      "FEVER": "No",
      "HAD_SYMPTOMS": "",
      "HEADACHE": "",
      "HEALTH_IMPACT": "N/A",
      "HEALTH_NOW": "",
      "HEALTH_NOW_COMPARISON": "",
      "VACCINE_CAUSED_HEALTH_ISSUES": "",
      "HEALTHCARE_VISITS": "",
      "ITCHING": "",
      "JOINT_PAINS": "",
      "MUSCLE_OR_BODY_ACHES": "",
      "NAUSEA": "",
      "PAIN": "",
      "PREGNANT": "",
      "PREGNANCY_TEST": "",
      "RASH_OUTSIDE_INJECTION_SITE": "",
      "REDNESS": "",
      "SITE_REACTION": "None",
      "SWELLING": "",
      "SYSTEMIC_REACTION": "None",
      "TEMPERATURE_CELSIUS": "",
      "TEMPERATURE_FAHRENHEIT": "",
      "TEMPERATURE_READING": "",
      "TESTED_POSITIVE": "",
      "TESTED_POSITIVE_DATE": "",
      "VOMITING": "",
      "DURATION_MINS": "0.18",
      "PREFERRED_LANGUAGE": "English",
      "REG_PREFIX": "6KM",
      "DOSE_NUM": "dose3",
      "TYPE": "daily",
      "MID_PHRASE": "-1-6-daily-",
      "SRO_MEDDRA": "",
      "SD_MEDDRA": "",
      "HCVO_MEDDRA": ""
    },
    {
      "SURVEY_STATIC_ID": "vsafe-1-6-daily-dose3",
      "REGISTRANT_CODE": "6KM-17719-80847",
      "RESPONSE_ID": "s269771112118003703480048785889138712197",
      "STARTED_ON": "09/01/2021",
      "STARTED_ON_TIME": "2:14:48 PM",
      "DAYS_SINCE": 5,
      "ABDOMINAL_PAIN": "",
      "CHILLS": "",
      "DIARRHEA": "",
      "FATIGUE": "",
      "FEELING_TODAY": "Good",
      "FEVER": "No",
      "HAD_SYMPTOMS": "",
      "HEADACHE": "",
      "HEALTH_IMPACT": "N/A",
      "HEALTH_NOW": "",
      "HEALTH_NOW_COMPARISON": "",
      "VACCINE_CAUSED_HEALTH_ISSUES": "",
      "HEALTHCARE_VISITS": "",
      "ITCHING": "",
      "JOINT_PAINS": "",
      "MUSCLE_OR_BODY_ACHES": "",
      "NAUSEA": "",
      "PAIN": "",
      "PREGNANT": "",
      "PREGNANCY_TEST": "",
      "RASH_OUTSIDE_INJECTION_SITE": "",
      "REDNESS": "",
      "SITE_REACTION": "None",
      "SWELLING": "",
      "SYSTEMIC_REACTION": "None",
      "TEMPERATURE_CELSIUS": "",
      "TEMPERATURE_FAHRENHEIT": "",
      "TEMPERATURE_READING": "",
      "TESTED_POSITIVE": "",
      "TESTED_POSITIVE_DATE": "",
      "VOMITING": "",
      "DURATION_MINS": "0.2",
      "PREFERRED_LANGUAGE": "English",
      "REG_PREFIX": "6KM",
      "DOSE_NUM": "dose3",
      "TYPE": "daily",
      "MID_PHRASE": "-1-6-daily-",
      "SRO_MEDDRA": "",
      "SD_MEDDRA": "",
      "HCVO_MEDDRA": ""
    },
    {
      "SURVEY_STATIC_ID": "vsafe-1-6-daily-dose3",
      "REGISTRANT_CODE": "6KM-17719-80847",
      "RESPONSE_ID": "s269878324975905942585788054904039410041",
      "STARTED_ON": "09/02/2021",
      "STARTED_ON_TIME": "3:00:56 PM",
      "DAYS_SINCE": 6,
      "ABDOMINAL_PAIN": "",
      "CHILLS": "",
      "DIARRHEA": "",
      "FATIGUE": "",
      "FEELING_TODAY": "Good",
      "FEVER": "No",
      "HAD_SYMPTOMS": "",
      "HEADACHE": "",
      "HEALTH_IMPACT": "N/A",
      "HEALTH_NOW": "",
      "HEALTH_NOW_COMPARISON": "",
      "VACCINE_CAUSED_HEALTH_ISSUES": "",
      "HEALTHCARE_VISITS": "",
      "ITCHING": "",
      "JOINT_PAINS": "",
      "MUSCLE_OR_BODY_ACHES": "",
      "NAUSEA": "",
      "PAIN": "",
      "PREGNANT": "",
      "PREGNANCY_TEST": "",
      "RASH_OUTSIDE_INJECTION_SITE": "",
      "REDNESS": "",
      "SITE_REACTION": "None",
      "SWELLING": "",
      "SYSTEMIC_REACTION": "None",
      "TEMPERATURE_CELSIUS": "",
      "TEMPERATURE_FAHRENHEIT": "",
      "TEMPERATURE_READING": "",
      "TESTED_POSITIVE": "",
      "TESTED_POSITIVE_DATE": "",
      "VOMITING": "",
      "DURATION_MINS": "0.17",
      "PREFERRED_LANGUAGE": "English",
      "REG_PREFIX": "6KM",
      "DOSE_NUM": "dose3",
      "TYPE": "daily",
      "MID_PHRASE": "-1-6-daily-",
      "SRO_MEDDRA": "",
      "SD_MEDDRA": "",
      "HCVO_MEDDRA": ""
    },
    {
      "SURVEY_STATIC_ID": "vsafe-7-day-dose3",
      "REGISTRANT_CODE": "6KM-17719-80847",
      "RESPONSE_ID": "s269982259615245359728879470461435119978",
      "STARTED_ON": "09/03/2021",
      "STARTED_ON_TIME": "2:46:38 PM",
      "DAYS_SINCE": 7,
      "ABDOMINAL_PAIN": "",
      "CHILLS": "",
      "DIARRHEA": "",
      "FATIGUE": "",
      "FEELING_TODAY": "Good",
      "FEVER": "No",
      "HAD_SYMPTOMS": "",
      "HEADACHE": "Mild",
      "HEALTH_IMPACT": "N/A",
      "HEALTH_NOW": "",
      "HEALTH_NOW_COMPARISON": "",
      "VACCINE_CAUSED_HEALTH_ISSUES": "",
      "HEALTHCARE_VISITS": "",
      "ITCHING": "",
      "JOINT_PAINS": "Mild",
      "MUSCLE_OR_BODY_ACHES": "Moderate",
      "NAUSEA": "",
      "PAIN": "",
      "PREGNANT": "",
      "PREGNANCY_TEST": "",
      "RASH_OUTSIDE_INJECTION_SITE": "",
      "REDNESS": "",
      "SITE_REACTION": "None",
      "SWELLING": "",
      "SYSTEMIC_REACTION": "Headache:Joint pains:Muscle or body aches",
      "TEMPERATURE_CELSIUS": "",
      "TEMPERATURE_FAHRENHEIT": "",
      "TEMPERATURE_READING": "",
      "TESTED_POSITIVE": "",
      "TESTED_POSITIVE_DATE": "",
      "VOMITING": "",
      "DURATION_MINS": "0.8",
      "PREFERRED_LANGUAGE": "English",
      "REG_PREFIX": "6KM",
      "DOSE_NUM": "dose3",
      "TYPE": "daily",
      "MID_PHRASE": "-7-day-",
      "SRO_MEDDRA": "Diarrhoea * Loose stools",
      "SD_MEDDRA": "",
      "HCVO_MEDDRA": ""
    },
    {
      "SURVEY_STATIC_ID": "vsafe-14-day-dose3",
      "REGISTRANT_CODE": "6KM-17719-80847",
      "RESPONSE_ID": "s270710788312246102121142881547706834311",
      "STARTED_ON": "09/10/2021",
      "STARTED_ON_TIME": "2:13:39 PM",
      "DAYS_SINCE": 14,
      "ABDOMINAL_PAIN": "",
      "CHILLS": "",
      "DIARRHEA": "",
      "FATIGUE": "",
      "FEELING_TODAY": "Good",
      "FEVER": "",
      "HAD_SYMPTOMS": "No",
      "HEADACHE": "",
      "HEALTH_IMPACT": "",
      "HEALTH_NOW": "",
      "HEALTH_NOW_COMPARISON": "",
      "VACCINE_CAUSED_HEALTH_ISSUES": "",
      "HEALTHCARE_VISITS": "",
      "ITCHING": "",
      "JOINT_PAINS": "",
      "MUSCLE_OR_BODY_ACHES": "",
      "NAUSEA": "",
      "PAIN": "",
      "PREGNANT": "",
      "PREGNANCY_TEST": "",
      "RASH_OUTSIDE_INJECTION_SITE": "",
      "REDNESS": "",
      "SITE_REACTION": "",
      "SWELLING": "",
      "SYSTEMIC_REACTION": "",
      "TEMPERATURE_CELSIUS": "",
      "TEMPERATURE_FAHRENHEIT": "",
      "TEMPERATURE_READING": "",
      "TESTED_POSITIVE": "No",
      "TESTED_POSITIVE_DATE": "",
      "VOMITING": "",
      "DURATION_MINS": "0.18",
      "PREFERRED_LANGUAGE": "English",
      "REG_PREFIX": "6KM",
      "DOSE_NUM": "dose3",
      "TYPE": "weekly",
      "MID_PHRASE": "-14-day-",
      "SRO_MEDDRA": "",
      "SD_MEDDRA": "",
      "HCVO_MEDDRA": ""
    },
    {
      "SURVEY_STATIC_ID": "vsafe-21-day-dose3",
      "REGISTRANT_CODE": "6KM-17719-80847",
      "RESPONSE_ID": "s271442836992359761605580361604140815789",
      "STARTED_ON": "09/17/2021",
      "STARTED_ON_TIME": "2:21:19 PM",
      "DAYS_SINCE": 21,
      "ABDOMINAL_PAIN": "",
      "CHILLS": "",
      "DIARRHEA": "",
      "FATIGUE": "",
      "FEELING_TODAY": "Good",
      "FEVER": "",
      "HAD_SYMPTOMS": "No",
      "HEADACHE": "",
      "HEALTH_IMPACT": "",
      "HEALTH_NOW": "",
      "HEALTH_NOW_COMPARISON": "",
      "VACCINE_CAUSED_HEALTH_ISSUES": "",
      "HEALTHCARE_VISITS": "",
      "ITCHING": "",
      "JOINT_PAINS": "",
      "MUSCLE_OR_BODY_ACHES": "",
      "NAUSEA": "",
      "PAIN": "",
      "PREGNANT": "",
      "PREGNANCY_TEST": "No",
      "RASH_OUTSIDE_INJECTION_SITE": "",
      "REDNESS": "",
      "SITE_REACTION": "",
      "SWELLING": "",
      "SYSTEMIC_REACTION": "",
      "TEMPERATURE_CELSIUS": "",
      "TEMPERATURE_FAHRENHEIT": "",
      "TEMPERATURE_READING": "",
      "TESTED_POSITIVE": "No",
      "TESTED_POSITIVE_DATE": "",
      "VOMITING": "",
      "DURATION_MINS": "0.28",
      "PREFERRED_LANGUAGE": "English",
      "REG_PREFIX": "6KM",
      "DOSE_NUM": "dose3",
      "TYPE": "weekly",
      "MID_PHRASE": "-21-day-",
      "SRO_MEDDRA": "",
      "SD_MEDDRA": "",
      "HCVO_MEDDRA": ""
    },
    {
      "SURVEY_STATIC_ID": "vsafe-28-day-dose3",
      "REGISTRANT_CODE": "6KM-17719-80847",
      "RESPONSE_ID": "s272172913273338887893865424376040141870",
      "STARTED_ON": "09/24/2021",
      "STARTED_ON_TIME": "2:06:22 PM",
      "DAYS_SINCE": 28,
      "ABDOMINAL_PAIN": "",
      "CHILLS": "",
      "DIARRHEA": "",
      "FATIGUE": "",
      "FEELING_TODAY": "Fair",
      "FEVER": "",
      "HAD_SYMPTOMS": "Yes",
      "HEADACHE": "",
      "HEALTH_IMPACT": "N/A",
      "HEALTH_NOW": "",
      "HEALTH_NOW_COMPARISON": "",
      "VACCINE_CAUSED_HEALTH_ISSUES": "",
      "HEALTHCARE_VISITS": "",
      "ITCHING": "",
      "JOINT_PAINS": "",
      "MUSCLE_OR_BODY_ACHES": "",
      "NAUSEA": "",
      "PAIN": "",
      "PREGNANT": "",
      "PREGNANCY_TEST": "",
      "RASH_OUTSIDE_INJECTION_SITE": "",
      "REDNESS": "",
      "SITE_REACTION": "",
      "SWELLING": "",
      "SYSTEMIC_REACTION": "",
      "TEMPERATURE_CELSIUS": "",
      "TEMPERATURE_FAHRENHEIT": "",
      "TEMPERATURE_READING": "",
      "TESTED_POSITIVE": "No",
      "TESTED_POSITIVE_DATE": "",
      "VOMITING": "",
      "DURATION_MINS": "1.05",
      "PREFERRED_LANGUAGE": "English",
      "REG_PREFIX": "6KM",
      "DOSE_NUM": "dose3",
      "TYPE": "weekly",
      "MID_PHRASE": "-28-day-",
      "SRO_MEDDRA": "",
      "SD_MEDDRA": "",
      "HCVO_MEDDRA": ""
    },
    {
      "SURVEY_STATIC_ID": "vsafe-35-day-dose3",
      "REGISTRANT_CODE": "6KM-17719-80847",
      "RESPONSE_ID": "s272904495619858553238091580076485914729",
      "STARTED_ON": "10/01/2021",
      "STARTED_ON_TIME": "2:12:21 PM",
      "DAYS_SINCE": 35,
      "ABDOMINAL_PAIN": "",
      "CHILLS": "",
      "DIARRHEA": "",
      "FATIGUE": "",
      "FEELING_TODAY": "Good",
      "FEVER": "",
      "HAD_SYMPTOMS": "No",
      "HEADACHE": "",
      "HEALTH_IMPACT": "",
      "HEALTH_NOW": "",
      "HEALTH_NOW_COMPARISON": "",
      "VACCINE_CAUSED_HEALTH_ISSUES": "",
      "HEALTHCARE_VISITS": "",
      "ITCHING": "",
      "JOINT_PAINS": "",
      "MUSCLE_OR_BODY_ACHES": "",
      "NAUSEA": "",
      "PAIN": "",
      "PREGNANT": "",
      "PREGNANCY_TEST": "",
      "RASH_OUTSIDE_INJECTION_SITE": "",
      "REDNESS": "",
      "SITE_REACTION": "",
      "SWELLING": "",
      "SYSTEMIC_REACTION": "",
      "TEMPERATURE_CELSIUS": "",
      "TEMPERATURE_FAHRENHEIT": "",
      "TEMPERATURE_READING": "",
      "TESTED_POSITIVE": "No",
      "TESTED_POSITIVE_DATE": "",
      "VOMITING": "",
      "DURATION_MINS": "0.15",
      "PREFERRED_LANGUAGE": "English",
      "REG_PREFIX": "6KM",
      "DOSE_NUM": "dose3",
      "TYPE": "weekly",
      "MID_PHRASE": "-35-day-",
      "SRO_MEDDRA": "",
      "SD_MEDDRA": "",
      "HCVO_MEDDRA": ""
    },
    {
      "SURVEY_STATIC_ID": "vsafe-42-day-dose3",
      "REGISTRANT_CODE": "6KM-17719-80847",
      "RESPONSE_ID": "s273856775766827695489753857164453761765",
      "STARTED_ON": "10/10/2021",
      "STARTED_ON_TIME": "5:00:39 PM",
      "DAYS_SINCE": 44,
      "ABDOMINAL_PAIN": "",
      "CHILLS": "",
      "DIARRHEA": "",
      "FATIGUE": "",
      "FEELING_TODAY": "Good",
      "FEVER": "",
      "HAD_SYMPTOMS": "No",
      "HEADACHE": "",
      "HEALTH_IMPACT": "",
      "HEALTH_NOW": "Fair",
      "HEALTH_NOW_COMPARISON": "About the same",
      "VACCINE_CAUSED_HEALTH_ISSUES": "",
      "HEALTHCARE_VISITS": "",
      "ITCHING": "",
      "JOINT_PAINS": "",
      "MUSCLE_OR_BODY_ACHES": "",
      "NAUSEA": "",
      "PAIN": "",
      "PREGNANT": "",
      "PREGNANCY_TEST": "No",
      "RASH_OUTSIDE_INJECTION_SITE": "",
      "REDNESS": "",
      "SITE_REACTION": "",
      "SWELLING": "",
      "SYSTEMIC_REACTION": "",
      "TEMPERATURE_CELSIUS": "",
      "TEMPERATURE_FAHRENHEIT": "",
      "TEMPERATURE_READING": "",
      "TESTED_POSITIVE": "No",
      "TESTED_POSITIVE_DATE": "",
      "VOMITING": "",
      "DURATION_MINS": "0.42",
      "PREFERRED_LANGUAGE": "English",
      "REG_PREFIX": "6KM",
      "DOSE_NUM": "dose3",
      "TYPE": "weekly",
      "MID_PHRASE": "-42-day-",
      "SRO_MEDDRA": "",
      "SD_MEDDRA": "",
      "HCVO_MEDDRA": ""
    },
    {
      "SURVEY_STATIC_ID": "vsafe-3-month-dose3",
      "REGISTRANT_CODE": "6KM-17719-80847",
      "RESPONSE_ID": "s278766627498270529579617066444751794486",
      "STARTED_ON": "11/26/2021",
      "STARTED_ON_TIME": "4:09:01 PM",
      "DAYS_SINCE": 91,
      "ABDOMINAL_PAIN": "",
      "CHILLS": "",
      "DIARRHEA": "",
      "FATIGUE": "",
      "FEELING_TODAY": "Good",
      "FEVER": "",
      "HAD_SYMPTOMS": "No",
      "HEADACHE": "",
      "HEALTH_IMPACT": "",
      "HEALTH_NOW": "",
      "HEALTH_NOW_COMPARISON": "About the same",
      "VACCINE_CAUSED_HEALTH_ISSUES": "",
      "HEALTHCARE_VISITS": "",
      "ITCHING": "",
      "JOINT_PAINS": "",
      "MUSCLE_OR_BODY_ACHES": "",
      "NAUSEA": "",
      "PAIN": "",
      "PREGNANT": "",
      "PREGNANCY_TEST": "No",
      "RASH_OUTSIDE_INJECTION_SITE": "",
      "REDNESS": "",
      "SITE_REACTION": "",
      "SWELLING": "",
      "SYSTEMIC_REACTION": "",
      "TEMPERATURE_CELSIUS": "",
      "TEMPERATURE_FAHRENHEIT": "",
      "TEMPERATURE_READING": "",
      "TESTED_POSITIVE": "No",
      "TESTED_POSITIVE_DATE": "",
      "VOMITING": "",
      "DURATION_MINS": "0.48",
      "PREFERRED_LANGUAGE": "English",
      "REG_PREFIX": "6KM",
      "DOSE_NUM": "dose3",
      "TYPE": "monthly",
      "MID_PHRASE": "-3-month-",
      "SRO_MEDDRA": "",
      "SD_MEDDRA": "",
      "HCVO_MEDDRA": ""
    },
    {
      "SURVEY_STATIC_ID": "vsafe-0-day-dose1",
      "REGISTRANT_CODE": "6KM-17719-80847",
      "RESPONSE_ID": "s243977962469716980550721335412176586289",
      "STARTED_ON": "12/28/2020",
      "STARTED_ON_TIME": "2:41:31 PM",
      "DAYS_SINCE": 0,
      "ABDOMINAL_PAIN": "",
      "CHILLS": "",
      "DIARRHEA": "",
      "FATIGUE": "",
      "FEELING_TODAY": "Good",
      "FEVER": "No",
      "HAD_SYMPTOMS": "",
      "HEADACHE": "",
      "HEALTH_IMPACT": "N/A",
      "HEALTH_NOW": "",
      "HEALTH_NOW_COMPARISON": "",
      "VACCINE_CAUSED_HEALTH_ISSUES": "",
      "HEALTHCARE_VISITS": "",
      "ITCHING": "",
      "JOINT_PAINS": "",
      "MUSCLE_OR_BODY_ACHES": "",
      "NAUSEA": "",
      "PAIN": "",
      "PREGNANT": "No",
      "PREGNANCY_TEST": "",
      "RASH_OUTSIDE_INJECTION_SITE": "",
      "REDNESS": "",
      "SITE_REACTION": "None",
      "SWELLING": "",
      "SYSTEMIC_REACTION": "None",
      "TEMPERATURE_CELSIUS": "",
      "TEMPERATURE_FAHRENHEIT": "",
      "TEMPERATURE_READING": "",
      "TESTED_POSITIVE": "",
      "TESTED_POSITIVE_DATE": "",
      "VOMITING": "",
      "DURATION_MINS": "",
      "PREFERRED_LANGUAGE": "English",
      "REG_PREFIX": "6KM",
      "DOSE_NUM": "dose1",
      "TYPE": "daily",
      "MID_PHRASE": "-0-day-",
      "SRO_MEDDRA": "",
      "SD_MEDDRA": "",
      "HCVO_MEDDRA": ""
    },
    {
      "SURVEY_STATIC_ID": "vsafe-1-6-daily-dose1",
      "REGISTRANT_CODE": "6KM-17719-80847",
      "RESPONSE_ID": "s244082089254515214956288932231686786175",
      "STARTED_ON": "12/29/2020",
      "STARTED_ON_TIME": "2:49:23 PM",
      "DAYS_SINCE": 1,
      "ABDOMINAL_PAIN": "",
      "CHILLS": "",
      "DIARRHEA": "",
      "FATIGUE": "",
      "FEELING_TODAY": "Good",
      "FEVER": "No",
      "HAD_SYMPTOMS": "",
      "HEADACHE": "",
      "HEALTH_IMPACT": "N/A",
      "HEALTH_NOW": "",
      "HEALTH_NOW_COMPARISON": "",
      "VACCINE_CAUSED_HEALTH_ISSUES": "",
      "HEALTHCARE_VISITS": "",
      "ITCHING": "",
      "JOINT_PAINS": "",
      "MUSCLE_OR_BODY_ACHES": "",
      "NAUSEA": "",
      "PAIN": "",
      "PREGNANT": "",
      "PREGNANCY_TEST": "",
      "RASH_OUTSIDE_INJECTION_SITE": "",
      "REDNESS": "",
      "SITE_REACTION": "None",
      "SWELLING": "",
      "SYSTEMIC_REACTION": "None",
      "TEMPERATURE_CELSIUS": "",
      "TEMPERATURE_FAHRENHEIT": "",
      "TEMPERATURE_READING": "",
      "TESTED_POSITIVE": "",
      "TESTED_POSITIVE_DATE": "",
      "VOMITING": "",
      "DURATION_MINS": "",
      "PREFERRED_LANGUAGE": "English",
      "REG_PREFIX": "6KM",
      "DOSE_NUM": "dose1",
      "TYPE": "daily",
      "MID_PHRASE": "-1-6-daily-",
      "SRO_MEDDRA": "",
      "SD_MEDDRA": "",
      "HCVO_MEDDRA": ""
    },
    {
      "SURVEY_STATIC_ID": "vsafe-1-6-daily-dose1",
      "REGISTRANT_CODE": "6KM-17719-80847",
      "RESPONSE_ID": "s244188684566333349668038882271720778360",
      "STARTED_ON": "12/30/2020",
      "STARTED_ON_TIME": "3:06:09 PM",
      "DAYS_SINCE": 2,
      "ABDOMINAL_PAIN": "",
      "CHILLS": "",
      "DIARRHEA": "",
      "FATIGUE": "",
      "FEELING_TODAY": "Good",
      "FEVER": "No",
      "HAD_SYMPTOMS": "",
      "HEADACHE": "",
      "HEALTH_IMPACT": "N/A",
      "HEALTH_NOW": "",
      "HEALTH_NOW_COMPARISON": "",
      "VACCINE_CAUSED_HEALTH_ISSUES": "",
      "HEALTHCARE_VISITS": "",
      "ITCHING": "",
      "JOINT_PAINS": "",
      "MUSCLE_OR_BODY_ACHES": "",
      "NAUSEA": "",
      "PAIN": "",
      "PREGNANT": "",
      "PREGNANCY_TEST": "",
      "RASH_OUTSIDE_INJECTION_SITE": "",
      "REDNESS": "",
      "SITE_REACTION": "None",
      "SWELLING": "",
      "SYSTEMIC_REACTION": "None",
      "TEMPERATURE_CELSIUS": "",
      "TEMPERATURE_FAHRENHEIT": "",
      "TEMPERATURE_READING": "",
      "TESTED_POSITIVE": "",
      "TESTED_POSITIVE_DATE": "",
      "VOMITING": "",
      "DURATION_MINS": "",
      "PREFERRED_LANGUAGE": "English",
      "REG_PREFIX": "6KM",
      "DOSE_NUM": "dose1",
      "TYPE": "daily",
      "MID_PHRASE": "-1-6-daily-",
      "SRO_MEDDRA": "",
      "SD_MEDDRA": "",
      "HCVO_MEDDRA": ""
    },
    {
      "SURVEY_STATIC_ID": "vsafe-1-6-daily-dose1",
      "REGISTRANT_CODE": "6KM-17719-80847",
      "RESPONSE_ID": "s244312701715983824011445498956546209628",
      "STARTED_ON": "12/31/2020",
      "STARTED_ON_TIME": "7:42:13 PM",
      "DAYS_SINCE": 3,
      "ABDOMINAL_PAIN": "",
      "CHILLS": "",
      "DIARRHEA": "",
      "FATIGUE": "",
      "FEELING_TODAY": "Good",
      "FEVER": "No",
      "HAD_SYMPTOMS": "",
      "HEADACHE": "",
      "HEALTH_IMPACT": "N/A",
      "HEALTH_NOW": "",
      "HEALTH_NOW_COMPARISON": "",
      "VACCINE_CAUSED_HEALTH_ISSUES": "",
      "HEALTHCARE_VISITS": "",
      "ITCHING": "",
      "JOINT_PAINS": "",
      "MUSCLE_OR_BODY_ACHES": "",
      "NAUSEA": "",
      "PAIN": "",
      "PREGNANT": "",
      "PREGNANCY_TEST": "",
      "RASH_OUTSIDE_INJECTION_SITE": "",
      "REDNESS": "",
      "SITE_REACTION": "None",
      "SWELLING": "",
      "SYSTEMIC_REACTION": "None",
      "TEMPERATURE_CELSIUS": "",
      "TEMPERATURE_FAHRENHEIT": "",
      "TEMPERATURE_READING": "",
      "TESTED_POSITIVE": "",
      "TESTED_POSITIVE_DATE": "",
      "VOMITING": "",
      "DURATION_MINS": "",
      "PREFERRED_LANGUAGE": "English",
      "REG_PREFIX": "6KM",
      "DOSE_NUM": "dose1",
      "TYPE": "daily",
      "MID_PHRASE": "-1-6-daily-",
      "SRO_MEDDRA": "",
      "SD_MEDDRA": "",
      "HCVO_MEDDRA": ""
    }
  ],
  "has_free_text": true,
  "num_free_text_checkins": 3,
  "num_unpublished": 1,
  "call_center": [
    {
      "REGISTRANT_CODE": "6KM-17719-80847",
      "RELATIONSHIP": "",
      "SEX": "FEMALE",
      "HEALTH_IMPACT": "Be unable to work or attend school:Be unable to do your normal daily activities:Get care from a doctor or other healthcare pr",
      "DOSE_NUMBER": 3,
      "DAYS_SINCE": 182,
      "TIME_ZONE": "US/Eastern",
      "REPORTED_DATE": "02/25/2022",
      "SURVEY_STATIC_ID": "vsafe-6-month-dose3",
      "MANUFACTURER": "Pfizer-BioNTech",
      "PREFERRED_LANGUAGE": "English",
      "CONSOLIDATED_PREGNANCY": "No",
      "AGE_AT_VX": "48.0",
      "HEALTHCARE_VISITS": "Telehealth, virtual health, or email health consultation",
      "ZIP_CODE": 293,
      "REG_CODE_PREFIX": "6KM"
    }
  ],
  "gdit": [
    {
      "RegistrantCode": "6KM-17719-80847",
      "SurveyStaticID": "vsafe-6-month-dose3",
      "Manufacturer": "Pfizer-BioNTech",
      "IsVaccineValid": "Correct",
      "UpdatedVaccine": "",
      "DoseNbr": 3,
      "DaysSinceVaccination": 182,
      "ReportedDate": "02/25/2022",
      "FinalOutcome": "Successful",
      "SuccessDate": "03/02/2022",
      "Call1Date": "",
      "Call1Outcome": "",
      "Call2Date": "",
      "Call2Outcome": "",
      "Call3Date": "",
      "Call3Outcome": "",
      "CallXDate": "",
      "CallXOutcome": "",
      "CallBackDate": "",
      "CallBackTime": "",
      "AllReportOutcomes": "Does not wish to fill out VAERS report",
      "DoNotContactRegistrant": "",
      "UpdatedPregnancy": "",
      "PossibleIssues": "",
      "AGE_AT_VX": "48.0",
      "REG_CODE_PREFIX": "6KM"
    }
  ]
}